{
  "$schema": "vscode://schemas/color-theme",
  "name": "Precious Dark Eleven",
  "colors": {
    "activityBar.activeBackground": "#292b2d",
    "activityBar.activeBorder": "#3e81b9",
    "activityBar.background": "#212325",
    "activityBar.border": "#3a3c3e",
    "activityBar.foreground": "#b8b7b6",
    "activityBar.inactiveForeground": "#797a7a",
    "activityBarBadge.background": "#3e81b9",
    "activityBarBadge.foreground": "#1c1e20",
    "badge.background": "#3e81b9",
    "badge.foreground": "#1c1e20",
    "banner.background": "#707171",
    "breadcrumb.activeSelectionForeground": "#b8b7b6",
    "breadcrumb.focusForeground": "#b8b7b6",
    "button.background": "#3e81b9",
    "button.border": "#3a3c3e",
    "button.foreground": "#1c1e20",
    "button.hoverBackground": "#3e81b9e6",
    "button.secondaryBackground": "#3a3c3e",
    "button.secondaryForeground": "#b8b7b6",
    "button.secondaryHoverBackground": "#b8b7b634",
    "charts.blue": "#3e81b9",
    "charts.green": "#5b8b3d",
    "charts.purple": "#9268bc",
    "charts.orange": "#b36a28",
    "charts.red": "#c65a56",
    "charts.yellow": "#9c770a",
    "checkbox.background": "#1c1e20",
    "checkbox.border": "#454748",
    "commandCenter.activeBackground": "#b8b7b614",
    "commandCenter.background": "#b8b7b60c",
    "debugExceptionWidget.background": "#4b2f2d",
    "debugExceptionWidget.border": "#8d514f",
    "debugIcon.breakpointCurrentStackframeForeground": "#9c770a",
    "debugIcon.breakpointDisabledForeground": "#797a7a",
    "debugIcon.breakpointForeground": "#c65a56",
    "debugIcon.breakpointStackframeForeground": "#708627",
    "debugIcon.breakpointUnverifiedForeground": "#797a7a",
    "debugIcon.continueForeground": "#3e81b9",
    "debugIcon.disconnectForeground": "#c65a56",
    "debugIcon.pauseForeground": "#3e81b9",
    "debugIcon.restartForeground": "#5b8b3d",
    "debugIcon.startForeground": "#5b8b3d",
    "debugIcon.stepBackForeground": "#3e81b9",
    "debugIcon.stepIntoForeground": "#3e81b9",
    "debugIcon.stepOutForeground": "#3e81b9",
    "debugIcon.stepOverForeground": "#3e81b9",
    "debugIcon.stopForeground": "#c65a56",
    "debugTokenExpression.boolean": "#68b0ee",
    "debugTokenExpression.error": "#ff8882",
    "debugTokenExpression.name": "#f189b4",
    "debugTokenExpression.number": "#ea9755",
    "debugTokenExpression.string": "#9bb553",
    "debugTokenExpression.value": "#a8a8a7",
    "debugToolBar.background": "#242628",
    "debugView.exceptionLabelBackground": "#ff8882",
    "debugView.exceptionLabelForeground": "#1c1e20",
    "debugView.stateLabelBackground": "#7d7e7e44",
    "debugView.valueChangedHighlight": "#2b4459",
    "descriptionForeground": "#b8b7b6",
    "diffEditor.diagonalFill": "#b8b7b633",
    "diffEditor.insertedLineBackground": "#5f9c5223",
    "diffEditor.insertedTextBackground": "#5f9c5247",
    "diffEditor.removedLineBackground": "#da686423",
    "diffEditor.removedTextBackground": "#da686447",
    "disabledForeground": "#797a7a",
    "dropdown.background": "#1c1e20",
    "dropdown.border": "#454748",
    "dropdown.foreground": "#b8b7b6",
    "dropdown.listBackground": "#1c1e20",
    "editor.background": "#1c1e20",
    "editor.findMatchBackground": "#253a51",
    "editor.findMatchBorder": "#89a23e",
    "editor.findMatchHighlightBackground": "#7e963355",
    "editor.findMatchHighlightBorder": "#89a23e",
    "editor.findRangeHighlightBackground": "#56575833",
    "editor.focusedStackFrameHighlightBackground": "#55385d",
    "editor.foreground": "#b8b7b6",
    "editor.hoverHighlightBackground": "#253a5140",
    "editor.inactiveSelectionBackground": "#282e33",
    "editor.inlineValuesBackground": "#b8b7b600",
    "editor.inlineValuesForeground": "#7f7f80",
    "editor.lineHighlightBackground": "#202224",
    "editor.lineHighlightBorder": "#20232a",
    "editor.linkedEditingBackground": "#c6773133",
    "editor.rangeHighlightBackground": "#5f9c5212",
    "editor.selectionBackground": "#253a51",
    "editor.selectionHighlightBackground": "#253a5180",
    "editor.snippetFinalTabstopHighlightBorder": "#7caaf97f",
    "editor.snippetTabstopHighlightBackground": "#7caaf933",
    "editor.stackFrameHighlightBackground": "#3a2a40",
    "editor.wordHighlightBackground": "#a277d226",
    "editor.wordHighlightStrongBackground": "#ce699326",
    "editorBracketHighlight.foreground1": "#c396f3",
    "editorBracketHighlight.foreground2": "#68b0ee",
    "editorBracketHighlight.foreground3": "#41bda7",
    "editorBracketHighlight.foreground4": "#9bb553",
    "editorBracketHighlight.foreground5": "#ea9755",
    "editorBracketHighlight.foreground6": "#f189b4",
    "editorBracketHighlight.unexpectedBracket.foreground": "#ff8882",
    "editorBracketMatch.background": "#13454f",
    "editorBracketMatch.border": "#13454f",
    "editorBracketPairGuide.activeBackground1": "#b8b7b600",
    "editorBracketPairGuide.activeBackground2": "#b8b7b600",
    "editorBracketPairGuide.activeBackground3": "#b8b7b600",
    "editorBracketPairGuide.activeBackground4": "#b8b7b600",
    "editorBracketPairGuide.activeBackground5": "#b8b7b600",
    "editorBracketPairGuide.activeBackground6": "#b8b7b600",
    "editorBracketPairGuide.background1": "#b8b7b600",
    "editorBracketPairGuide.background2": "#b8b7b600",
    "editorBracketPairGuide.background3": "#b8b7b600",
    "editorBracketPairGuide.background4": "#b8b7b600",
    "editorBracketPairGuide.background5": "#b8b7b600",
    "editorBracketPairGuide.background6": "#b8b7b600",
    "editorCodeLens.foreground": "#757576",
    "editorCursor.foreground": "#b8b7b6",
    "editorError.foreground": "#e9736f",
    "editorGhostText.foreground": "#b8b7b677",
    "editorGroup.border": "#3a3c3e",
    "editorGroup.dropBackground": "#548bce33",
    "editorGroupHeader.tabsBackground": "#212325",
    "editorGroupHeader.tabsBorder": "#3a3c3e",
    "editorGutter.addedBackground": "#47613a",
    "editorGutter.commentRangeForeground": "#b8b7b619",
    "editorGutter.deletedBackground": "#824845",
    "editorGutter.modifiedBackground": "#375b79",
    "editorHint.foreground": "#949393",
    "editorHoverWidget.statusBarBackground": "#26282a",
    "editorIndentGuide.activeBackground": "#424345",
    "editorIndentGuide.background": "#292b2d",
    "editorInfo.foreground": "#4181b6",
    "editorInlayHint.background": "#6c768133",
    "editorInlayHint.foreground": "#6c7681",
    "editorInlayHint.typeBackground": "#6c768133",
    "editorInlayHint.typeForeground": "#6c7681",
    "editorLightBulb.foreground": "#9c770a",
    "editorLightBulbAutoFix.foreground": "#3e81b9",
    "editorLineNumber.activeForeground": "#8a8d9e",
    "editorLineNumber.foreground": "#515664",
    "editorLink.activeForeground": "#68b0ee",
    "editorOverviewRuler.border": "#3a3c3e",
    "editorOverviewRuler.bracketMatchForeground": "#676868",
    "editorOverviewRuler.errorForeground": "#da6864cc",
    "editorOverviewRuler.findMatchForeground": "#7e9633cc",
    "editorOverviewRuler.selectionHighlightForeground": "#a277d2cc",
    "editorOverviewRuler.wordHighlightForeground": "#a277d2cc",
    "editorOverviewRuler.wordHighlightStrongForeground": "#ce6993cc",
    "editorRuler.foreground": "#3d3e40",
    "editorStickyScrollHover.background": "#26282a",
    "editorSuggestWidget.background": "#212325",
    "editorUnnecessaryCode.opacity": "#0007",
    "editorWarning.foreground": "#bb922d",
    "editorWhitespace.foreground": "#b8b7b633",
    "editorWidget.background": "#1c1e20",
    "editorWidget.border": "#454648",
    "errorForeground": "#ff8882",
    "extensionIcon.preReleaseForeground": "#008e7b",
    "extensionIcon.sponsorForeground": "#ba5b84",
    "extensionIcon.starForeground": "#9c770a",
    "focusBorder": "#3e81b9",
    "foreground": "#b8b7b6",
    "gitDecoration.addedResourceForeground": "#83b965",
    "gitDecoration.conflictingResourceForeground": "#ff8882",
    "gitDecoration.deletedResourceForeground": "#929191",
    "gitDecoration.ignoredResourceForeground": "#9b8e3e",
    "gitDecoration.modifiedResourceForeground": "#68b0ee",
    "gitDecoration.renamedResourceForeground": "#41bda7",
    "gitDecoration.stageDeletedResourceForeground": "#c396f3",
    "gitDecoration.stageModifiedResourceForeground": "#5990c0",
    "gitDecoration.submoduleResourceForeground": "#b8b7b6",
    "gitDecoration.untrackedResourceForeground": "#ea9755",
    "icon.foreground": "#8c8c8c",
    "input.background": "#1c1e20",
    "input.border": "#454748",
    "input.foreground": "#b8b7b6",
    "input.placeholderForeground": "#b8b7b679",
    "inputOption.activeBackground": "#3e81b941",
    "inputOption.activeBorder": "#3e81b9",
    "inputOption.activeForeground": "#b8b7b6",
    "inputOption.hoverBackground": "#52545550",
    "inputValidation.errorBackground": "#262123",
    "inputValidation.errorBorder": "#e9736f",
    "inputValidation.infoBackground": "#1e232a",
    "inputValidation.infoBorder": "#4181b6",
    "inputValidation.warningBackground": "#24231f",
    "inputValidation.warningBorder": "#bb922d",
    "keybindingLabel.background": "#34363766",
    "keybindingLabel.border": "#42434566",
    "keybindingLabel.bottomBorder": "#50515266",
    "keybindingLabel.foreground": "#b8b7b6",
    "list.activeSelectionBackground": "#253a51",
    "list.activeSelectionForeground": "#b8b7b6",
    "list.activeSelectionIconForeground": "#b8b7b6",
    "list.deemphasizedForeground": "#777778",
    "list.dropBackground": "#61a0d726",
    "list.errorForeground": "#ff8882",
    "list.focusAndSelectionOutline": "#3e81b900",
    "list.highlightForeground": "#68b0ee",
    "list.hoverBackground": "#20272f",
    "list.inactiveSelectionBackground": "#343637",
    "list.invalidItemForeground": "#ea9755",
    "list.warningForeground": "#d0a543",
    "listFilterWidget.background": "#1c1e20",
    "listFilterWidget.noMatchesOutline": "#ff8882",
    "listFilterWidget.outline": "#b8b7b600",
    "menu.border": "#343637",
    "menu.separatorBackground": "#343637",
    "merge.commonContentBackground": "#96969538",
    "merge.commonHeaderBackground": "#96969547",
    "merge.currentContentBackground": "#049e8938",
    "merge.currentHeaderBackground": "#049e8947",
    "merge.incomingContentBackground": "#a277d238",
    "merge.incomingHeaderBackground": "#a277d247",
    "mergeEditor.change.background": "#5f9c5223",
    "mergeEditor.change.word.background": "#5f9c5247",
    "mergeEditor.changeBase.background": "#da686423",
    "mergeEditor.changeBase.word.background": "#da686447",
    "mergeEditor.conflict.handled.minimapOverViewRuler": "#5e5d5bee",
    "mergeEditor.conflict.handledFocused.border": "#4a4c4dcc",
    "mergeEditor.conflict.handledUnfocused.border": "#7f7f8049",
    "mergeEditor.conflict.unhandled.minimapOverViewRuler": "#b36a28",
    "mergeEditor.conflict.unhandledFocused.border": "#b36a28",
    "mergeEditor.conflict.unhandledUnfocused.border": "#b36a28",
    "mergeEditor.conflictingLines.background": "#c6773147",
    "minimap.errorHighlight": "#da6864cc",
    "minimap.findMatchHighlight": "#7e9633cc",
    "minimap.foregroundOpacity": "#000f",
    "minimap.selectionHighlight": "#253a51",
    "minimap.selectionOccurrenceHighlight": "#a277d266",
    "notebook.cellBorderColor": "#2c2e2f",
    "notebook.cellStatusBarItemHoverBackground": "#b8b7b614",
    "notebook.cellToolbarSeparator": "#85858559",
    "notebook.selectedCellBackground": "#2a3c4d50",
    "notebook.symbolHighlightBackground": "#3c3e2450",
    "notificationCenterHeader.background": "#1c1e20",
    "notificationCenterHeader.foreground": "#b8b7b6",
    "notifications.background": "#1c1e20",
    "notifications.border": "#3a3c3e",
    "notifications.foreground": "#b8b7b6",
    "panel.background": "#212325",
    "panel.border": "#3a3c3e",
    "panelInput.border": "#3a3c3e",
    "panelSectionHeader.background": "#85858533",
    "panelTitle.activeBorder": "#3e81b9",
    "panelTitle.activeForeground": "#b8b7b6",
    "panelTitle.inactiveForeground": "#b8b7b6",
    "peekViewEditor.background": "#1f2123",
    "peekViewEditor.matchHighlightBackground": "#7e963355",
    "peekViewEditor.matchHighlightBorder": "#89a23e",
    "peekViewResult.background": "#1c1e20",
    "peekViewResult.fileForeground": "#b8b7b6",
    "peekViewResult.lineForeground": "#999998",
    "peekViewResult.matchHighlightBackground": "#7e963355",
    "peekViewResult.selectionBackground": "#253a5180",
    "peekViewResult.selectionForeground": "#949393",
    "peekViewTitle.background": "#242628",
    "peekViewTitleDescription.foreground": "#9b9b9a",
    "peekViewTitleLabel.foreground": "#b8b7b6",
    "pickerGroup.border": "#3a3c3e",
    "pickerGroup.foreground": "#6c7681",
    "ports.iconRunningProcessForeground": "#5b8b3d",
    "profileBadge.background": "#48494b",
    "profileBadge.foreground": "#b8b7b6",
    "progressBar.background": "#3e81b9",
    "quickInput.background": "#1c1e20",
    "quickInput.foreground": "#b8b7b6",
    "quickInputTitle.background": "#b8b7b60f",
    "scm.providerBorder": "#454648",
    "scrollbar.shadow": "#a5acb633",
    "scrollbarSlider.activeBackground": "#8a8a8a47",
    "scrollbarSlider.background": "#8a8a8a33",
    "scrollbarSlider.hoverBackground": "#8a8a8a47",
    "searchEditor.textInputBorder": "#454748",
    "settings.dropdownBackground": "#1c1e20",
    "settings.dropdownBorder": "#454748",
    "settings.headerForeground": "#b8b7b6",
    "settings.modifiedItemIndicator": "#375b79",
    "settings.numberInputBorder": "#454748",
    "settings.textInputBorder": "#454748",
    "sideBar.background": "#1c1e20",
    "sideBar.border": "#3a3c3e",
    "sideBar.foreground": "#b8b7b6",
    "sideBarSectionHeader.background": "#212325",
    "sideBarSectionHeader.border": "#3a3c3e",
    "sideBarSectionHeader.foreground": "#b8b7b6",
    "sideBarTitle.foreground": "#b8b7b6",
    "statusBar.background": "#212325",
    "statusBar.border": "#3a3c3e",
    "statusBar.debuggingBackground": "#2f2626",
    "statusBar.debuggingForeground": "#b8b7b6",
    "statusBar.focusBorder": "#3e81b9",
    "statusBar.foreground": "#b8b7b6",
    "statusBar.noFolderBackground": "#212325",
    "statusBarItem.activeBackground": "#1c1e202d",
    "statusBarItem.compactHoverBackground": "#1c1e2033",
    "statusBarItem.errorBackground": "#c65a56",
    "statusBarItem.errorForeground": "#1c1e20",
    "statusBarItem.focusBorder": "#3e81b9",
    "statusBarItem.hoverBackground": "#1c1e201e",
    "statusBarItem.prominentBackground": "#878f9966",
    "statusBarItem.prominentHoverBackground": "#b8b7b64c",
    "statusBarItem.remoteBackground": "#3e81b9",
    "statusBarItem.remoteForeground": "#1c1e20",
    "statusBarItem.warningBackground": "#9c770a",
    "statusBarItem.warningForeground": "#1c1e20",
    "symbolIcon.classForeground": "#008e7b",
    "symbolIcon.constructorForeground": "#3e81b9",
    "symbolIcon.enumeratorForeground": "#008e7b",
    "symbolIcon.enumeratorMemberForeground": "#ba5b84",
    "symbolIcon.eventForeground": "#ba5b84",
    "symbolIcon.fieldForeground": "#ba5b84",
    "symbolIcon.functionForeground": "#3e81b9",
    "symbolIcon.interfaceForeground": "#008e7b",
    "symbolIcon.methodForeground": "#3e81b9",
    "symbolIcon.variableForeground": "#8c8c8c",
    "tab.activeBackground": "#1c1e20",
    "tab.activeBorder": "#212325",
    "tab.activeBorderTop": "#4e80b2",
    "tab.activeForeground": "#b8b7b6",
    "tab.activeModifiedBorder": "#3e81b9",
    "tab.border": "#3a3c3e",
    "tab.hoverBackground": "#1c1e20",
    "tab.inactiveBackground": "#212325",
    "tab.inactiveForeground": "#b8b7b680",
    "tab.lastPinnedBorder": "#b8b7b630",
    "tab.unfocusedActiveBorder": "#212325",
    "tab.unfocusedActiveBorderTop": "#b8b7b615",
    "tab.unfocusedHoverBackground": "#878f991a",
    "terminal.ansiBlack": "#b8b7b6",
    "terminal.ansiBlue": "#68b0ee",
    "terminal.ansiBrightBlack": "#b8b7b6",
    "terminal.ansiBrightBlue": "#68b0ee",
    "terminal.ansiBrightCyan": "#41bda7",
    "terminal.ansiBrightGreen": "#9bb553",
    "terminal.ansiBrightMagenta": "#c396f3",
    "terminal.ansiBrightRed": "#ff8882",
    "terminal.ansiBrightWhite": "#292b2d",
    "terminal.ansiBrightYellow": "#d0a543",
    "terminal.ansiCyan": "#41bda7",
    "terminal.ansiGreen": "#9bb553",
    "terminal.ansiMagenta": "#c396f3",
    "terminal.ansiRed": "#ff8882",
    "terminal.ansiWhite": "#858585",
    "terminal.ansiYellow": "#d0a543",
    "terminal.background": "#1c1e20",
    "terminal.findMatchBackground": "#253a51",
    "terminal.findMatchBorder": "#89a23e",
    "terminal.findMatchHighlightBackground": "#7e963355",
    "terminal.findMatchHighlightBorder": "#89a23e",
    "terminal.foreground": "#b8b7b6",
    "terminal.inactiveSelectionBackground": "#282e33",
    "terminal.tab.activeBorder": "#3e81b9",
    "terminalCommandDecoration.defaultBackground": "#b8b7b640",
    "terminalCommandDecoration.errorBackground": "#ff8882",
    "terminalCommandDecoration.successBackground": "#68b0ee",
    "terminalCursor.foreground": "#b8b7b6",
    "terminalOverviewRuler.cursorForeground": "#676868cc",
    "testing.iconErrored": "#c65a56",
    "testing.iconFailed": "#c65a56",
    "testing.iconPassed": "#5b8b3d",
    "testing.iconQueued": "#9c770a",
    "testing.iconSkipped": "#818282",
    "testing.iconUnset": "#818282",
    "testing.message.error.lineBackground": "#e9736f33",
    "textBlockQuote.background": "#212325",
    "textBlockQuote.border": "#3a3c3e",
    "textCodeBlock.background": "#252729",
    "textLink.activeForeground": "#68b0ee",
    "textLink.foreground": "#68b0ee",
    "textPreformat.foreground": "#9bb553",
    "textSeparator.foreground": "#b0b6bf",
    "titleBar.activeBackground": "#212325",
    "titleBar.activeForeground": "#b8b7b6",
    "titleBar.border": "#3a3c3e",
    "titleBar.inactiveBackground": "#212325",
    "titleBar.inactiveForeground": "#6c7681",
    "toolbar.activeBackground": "#6a6b6b50",
    "toolbar.hoverBackground": "#52545550",
    "tree.indentGuidesStroke": "#2f3132",
    "tree.tableColumnsBorder": "#9b9b9a20",
    "walkThrough.embeddedEditorBackground": "#242628",
    "walkthrough.stepTitle.foreground": "#b8b7b6",
    "welcomePage.tileBackground": "#242628",
    "welcomePage.tileBorder": "#3a3c3e",
    "welcomePage.tileHoverBackground": "#313234",
    "widget.border": "#3a3c3e",
    "widget.shadow": "#b8b7b628",
  },
  "tokenColors": [
    {
      "scope": "emphasis",
      "settings": {
        "fontStyle": "italic"
      }
    },
    {
      "scope": "strong",
      "settings": {
        "fontStyle": "bold"
      }
    },
    {
      "scope": "markup.underline",
      "settings": {
        "fontStyle": "underline"
      }
    },
    {
      "scope": "markup.bold",
      "settings": {
        "fontStyle": "bold"
      }
    },
    {
      "scope": "markup.italic",
      "settings": {
        "fontStyle": "italic"
      }
    },
    {
      "scope": "markup.strikethrough",
      "settings": {
        "fontStyle": "strikethrough"
      }
    },
    {
      "scope": [
        "constant.other.option",
        "constant.other.placeholder",
        "entity.name.variable",
        "keyword.operator",
        "keyword.operator.negation.regexp",
        "meta.definition.variable.name",
        "meta.embedded",
        "meta.function-call.arguments",
        "meta.function.parameters",
        "meta.indexed-name",
        "meta.template.expression",
        "punctuation",
        "source.groovy.embedded",
        "storage.modifier.chomping-indicator.yaml",
        "storage.modifier.flag.regexp",
        "storage.modifier.import.java",
        "storage.modifier.package.java",
        "string meta.image.inline.markdown",
        "string.unquoted",
        "support.other.parenthesis.regexp",
        "support.variable",
        "text",
        "variable",
        "variable.language.wildcard.java"
      ],
      "settings": {
        "foreground": "#b8b7b6"
      }
    },
    {
      "scope": [
        "entity.name.label",
        "keyword.operator.heredoc.php"
      ],
      "settings": {
        "foreground": "#b8b7b6",
        "fontStyle": "underline"
      }
    },
    {
      "scope": [
        "variable.parameter.preprocessor"
      ],
      "settings": {
        "foreground": "#b8b7b6",
        "fontStyle": "bold"
      }
    },
    {
      "scope": [
        "comment string.quoted"
      ],
      "settings": {
        "foreground": "#aeadac",
        "fontStyle": "italic"
      }
    },
    {
      "scope": [
        "comment",
        "punctuation.comment.begin",
        "punctuation.definition.comment",
        "string.quoted.docstring"
      ],
      "settings": {
        "foreground": "#858585",
        "fontStyle": "italic"
      }
    },
    {
      "scope": [
        "keyword.other.documentation",
        "keyword.other.phpdoc.php",
        "comment entity.other.attribute-name",
        "storage.type.class.doxygen"
      ],
      "settings": {
        "foreground": "#858585",
        "fontStyle": "italic underline"
      }
    },
    {
      "scope": [
        "comment entity.name.tag",
        "meta.shebang.shell"
      ],
      "settings": {
        "foreground": "#858585",
        "fontStyle": "italic bold"
      }
    },
    {
      "scope": [
        "invalid",
        "markup.deleted"
      ],
      "settings": {
        "foreground": "#ff8882"
      }
    },
    {
      "scope": [
        "invalid.deprecated",
      ],
      "settings": {
        "foreground": "#ff8882",
        "fontStyle": "strikethrough"
      }
    },
    {
      "scope": [
        "constant.numeric",
        "constant.sha.git-rebase",
        "keyword.operator.minus.exponent",
        "keyword.operator.plus.exponent",
        "keyword.operator.quantifier.regexp",
        "keyword.other.unit",
        "meta.preprocessor.numeric"
      ],
      "settings": {
        "foreground": "#ea9755"
      }
    },
    {
      "scope": [
        "entity.alias.import.go",
        "entity.name.function.decorator.python",
        "entity.name.function.macro",
        "entity.name.package.go",
        "entity.name.type.annotation",
        "keyword.control.directive",
        "keyword.operator.macro.dollar.rust",
        "meta.attribute.rust",
        "storage.type.annotation",
        "text.html.php support.attribute",
        "variable.other.metavariable.specifier.rust"
      ],
      "settings": {
        "foreground": "#d0a543"
      }
    },
    {
      "scope": [
        "entity.name.function.preprocessor"
      ],
      "settings": {
        "foreground": "#d0a543",
        "fontStyle": "bold"
      }
    },
    {
      "scope": [
        "constant.other.color.rgb-value",
        "constant.other.rgb-value",
        "markup.fenced_code.block.markdown",
        "markup.inline.raw",
        "markup.inserted",
        "markup.raw.block.markdown",
        "markup.quote.markdown",
        "meta.embedded.assembly",
        "meta.preprocessor.string",
        "meta.property-value",
        "meta.structure.dictionary.key.python",
        "string",
        "support.constant.color",
        "support.constant.font-name",
        "support.constant.media",
        "support.constant.media-type",
        "support.constant.property-value",
        "support.function.git-rebase",
        "variable.parameter.url.css"
      ],
      "settings": {
        "foreground": "#9bb553"
      }
    },
    {
      "scope": [
        "string.regexp"
      ],
      "settings": {
        "foreground": "#8ab861"
      }
    },
    {
      "scope": [
        "constant.character.character-class.regexp",
        "constant.other.character-class.regexp",
        "constant.other.character-class.set.regexp",
        "constant.other.database-name",
        "constant.other.table-name",
        "entity.name.class",
        "entity.name.function.target.makefile",
        "entity.name.namespace",
        "entity.name.scope-resolution",
        "entity.name.type",
        "entity.other.attribute",
        "entity.other.inherited-class",
        "meta.type.cast.expr",
        "meta.type.new.expr",
        "punctuation.definition.constant.xml",
        "storage.type.cs",
        "storage.type.generic.cs",
        "storage.type.generic.groovy",
        "storage.type.generic.java",
        "storage.type.groovy",
        "storage.type.java",
        "storage.type.modifier.cs",
        "storage.type.object.array.groovy",
        "storage.type.object.array.java",
        "storage.type.parameters.groovy",
        "storage.type.token.java",
        "storage.type.variable.cs",
        "support.class",
        "support.constant.dom",
        "support.constant.json",
        "support.constant.math",
        "support.other.escape.special.regexp",
        "support.type",
        "text.html constant.character.entity",
        "text.xml constant.character.entity"
      ],
      "settings": {
        "foreground": "#41bda7"
      }
    },
    {
      "scope": [
        "entity.name.command",
        "entity.name.function",
        "entity.name.operator.custom-literal",
        "entity.name.type.anchor.yaml",
        "entity.other.attribute-name",
        "keyword.other.definition.ini",
        "markup.changed",
        "markup.underline.link.markdown",
        "meta.function-call.generic.python",
        "meta.scope.prerequisites.makefile",
        "punctuation.definition.evaluation.backticks.shell",
        "punctuation.definition.evaluation.parens.begin.shell",
        "source.coffee.embedded",
        "source.powershell variable.other.member",
        "support.constant.handlebars",
        "support.constant.java-properties",
        "support.function",
        "support.type.property-name",
        "support.type.vendored.property-name",
        "variable.css",
        "variable.language.documentroot.xml",
        "variable.other.alias.yaml",
        "variable.other.metavariable.name.rust"
      ],
      "settings": {
        "foreground": "#68b0ee"
      }
    },
    {
      "scope": [
        "markup.underline.link.image.markdown",
        "variable.parameter.function-call"
      ],
      "settings": {
        "foreground": "#97a3fc"
      }
    },
    {
      "scope": [
        "entity.name.type.lifetime.rust"
      ],
      "settings": {
        "foreground": "#97a3fc",
        "fontStyle": "italic"
      }
    },
    {
      "scope": [
        "constant.character.entity",
        "constant.character.escape",
        "constant.language",
        "constant.other.color.rgb-value",
        "constant.other.rgb-value",
        "constant.other.reference.link.markdown",
        "entity.name.operator",
        "entity.name.section.group-title.ini",
        "entity.name.selector",
        "entity.name.tag",
        "entity.name.type.numeric.rust",
        "entity.other.attribute-name.class.css",
        "entity.other.attribute-name.class.mixin.css",
        "entity.other.attribute-name.id.css",
        "entity.other.attribute-name.parent-selector.css",
        "entity.other.attribute-name.pseudo-class.css",
        "entity.other.attribute-name.pseudo-element.css",
        "entity.other.attribute-name.css",
        "entity.other.attribute-name.scss",
        "keyword",
        "keyword.control",
        "keyword.control",
        "keyword.control.anchor.regexp",
        "keyword.operator.alignas",
        "keyword.operator.alignof",
        "keyword.operator.cast",
        "keyword.operator.disjunction.regexp",
        "keyword.operator.expression",
        "keyword.operator.instanceof",
        "keyword.operator.logical.python",
        "keyword.operator.new",
        "keyword.operator.noexcept",
        "keyword.operator.or.regexp",
        "keyword.operator.sizeof",
        "keyword.operator.typeid",
        "keyword.operator.wordlike",
        "keyword.other.operator",
        "keyword.other.using",
        "meta.at-rule.extend.scss",
        "meta.diff.header",
        "meta.object-literal.key",
        "meta.selector",
        "meta.separator.markdown",
        "punctuation.definition.bold.markdown",
        "punctuation.definition.italic.markdown",
        "punctuation.definition.strikethrough.markdown",
        "punctuation.definition.string.heredoc.shell",
        "punctuation.definition.template-expression.begin",
        "punctuation.definition.template-expression.end",
        "punctuation.definition.variable.shell",
        "punctuation.section.embedded",
        "punctuation.section.embedded.begin.php",
        "punctuation.section.embedded.end.php",
        "source.cpp keyword.operator.delete",
        "source.cpp keyword.operator.new",
        "source.css.less entity.other.attribute-name.id",
        "storage",
        "storage.modifier",
        "storage.type",
        "storage.type.boolean.go",
        "storage.type.byte.go",
        "storage.type.error.go",
        "storage.type.numeric.go",
        "storage.type.rune.go",
        "storage.type.string.go",
        "storage.type.uintptr.go",
        "support.constant.color",
        "support.constant.font-name",
        "support.constant.media",
        "support.constant.media-type",
        "support.constant.property-value",
        "support.function.builtin.python",
        "support.other.match.begin.regexp",
        "support.other.match.end.regexp",
        "source.css support.function",
        "source.makefile support.function",
        "source.toml support.type.property-name",
        "support.type.primitive",
        "variable.language"
      ],
      "settings": {
        "foreground": "#c396f3"
      }
    },
    {
      "scope": [
        "support.function.magic",
        "support.variable.magic"
      ],
      "settings": {
        "foreground": "#e08cd9"
      }
    },
    {
      "scope": [
        "constant.regexp",
        "entity.name.tag.namespace",
        "entity.name.variable.event",
        "entity.name.variable.field",
        "entity.name.variable.property",
        "entity.other.attribute-name.namespace",
        "markup.heading",
        "punctuation.definition.heading.markdown",
        "support.type.property-name.json",
        "variable.other.event",
        "variable.other.object.property",
        "variable.other.less",
        "variable.scss",
        "variable.other.property"
      ],
      "settings": {
        "foreground": "#f189b4"
      }
    },
    {
      "scope": [
        "constant.other.enum",
        "variable.other.enummember"
      ],
      "settings": {
        "foreground": "#f189b4",
        "fontStyle": "italic"
      }
    }
  ],
  "semanticHighlighting": true,
  "semanticTokenColors": {
    "namespace": {
      "foreground": "#41bda7"
    },
    "namespace:go": {
      "foreground": "#d0a543"
    },
    "class": {
      "foreground": "#41bda7"
    },
    "enum": {
      "foreground": "#41bda7"
    },
    "interface": {
      "foreground": "#41bda7"
    },
    "struct": {
      "foreground": "#41bda7"
    },
    "typeParameter": {
      "foreground": "#41bda7"
    },
    "type": {
      "foreground": "#41bda7"
    },
    "type.builtin": {
      "foreground": "#c396f3"
    },
    "type.defaultLibrary:go": {
      "foreground": "#c396f3"
    },
    "parameter": {
      "foreground": "#b8b7b6"
    },
    "parameter.modification": {
      "foreground": "#b8b7b6",
      "fontStyle": "underline"
    },
    "variable": {
      "foreground": "#b8b7b6"
    },
    "property": {
      "foreground": "#f189b4"
    },
    "enumMember": {
      "foreground": "#f189b4",
      "fontStyle": "italic"
    },
    "decorator": {
      "foreground": "#d0a543"
    },
    "event": {
      "foreground": "#f189b4"
    },
    "function": {
      "foreground": "#68b0ee"
    },
    "function.builtin": {
      "foreground": "#c396f3"
    },
    "function.defaultLibrary:go": {
      "foreground": "#c396f3"
    },
    "magicFunction:python": {
      "foreground": "#e08cd9"
    },
    "method": {
      "foreground": "#68b0ee"
    },
    "macro": {
      "foreground": "#d0a543"
    },
    "label": {
      "foreground": "#b8b7b6",
      "fontStyle": "underline"
    },
    "comment": {
      "foreground": "#858585"
    },
    "string": {
      "foreground": "#9bb553"
    },
    "keyword": {
      "foreground": "#c396f3"
    },
    "number": {
      "foreground": "#ea9755"
    },
    "regexp": {
      "foreground": "#8ab861"
    },
    "operator": {
      "foreground": "#b8b7b6"
    },
    "operatorOverload": {
      "foreground": "#68b0ee"
    },
    "memberOperatorOverload": {
      "foreground": "#68b0ee"
    },
    "selfParameter": {
      "foreground": "#c396f3"
    },
    "module": {
      "foreground": "#b8b7b6"
    },
    "newOperator": {
      "foreground": "#c396f3"
    },
    "stringLiteral": {
      "foreground": "#9bb553"
    },
    "customLiteral": {
      "foreground": "#e08cd9"
    },
    "numberLiteral": {
      "foreground": "#ea9755"
    },
    "*.decorator": {
      "foreground": "#d0a543"
    },
    "*.static": {
      "fontStyle": "italic"
    },
    "*.deprecated": {
      "fontStyle": "strikethrough"
    }
  }
}